synapse_graph/__init__.py
synapse_graph/graph.py
synapse_graph-0.5.4.dist-info/LICENSE
synapse_graph-0.5.4.dist-info/WHEEL
synapse_graph-0.5.4.dist-info/METADATA
synapse_graph-0.5.4.dist-info/RECORD
